thunk_dict/ThunkDict.py
thunk_dict/__init__.py
thunk_dict-0.1.1.dist-info/LICENSE.md
thunk_dict-0.1.1.dist-info/METADATA
thunk_dict-0.1.1.dist-info/WHEEL
thunk_dict-0.1.1.dist-info/top_level.txt
thunk_dict-0.1.1.dist-info/RECORD
